times_ctr_optimizer/__init__.py
times_ctr_optimizer/core/__init__.py
times_ctr_optimizer/core/data_generator.py
times_ctr_optimizer/core/feature_store.py
times_ctr_optimizer/core/models.py
times_ctr_optimizer/utils/__init__.py
times_ctr_optimizer-1.0.1.dist-info/licenses/LICENSE
times_ctr_optimizer-1.0.1.dist-info/METADATA
times_ctr_optimizer-1.0.1.dist-info/WHEEL
times_ctr_optimizer-1.0.1.dist-info/entry_points.txt
times_ctr_optimizer-1.0.1.dist-info/top_level.txt
times_ctr_optimizer-1.0.1.dist-info/RECORD
