Metadata-Version: 2.4
Name: times-ctr-optimizer
Version: 1.0.1
Summary: Professional CTR optimization achieving 20.4% performance - Production-ready recommendation system by MTech AI student at IIT Patna
Author-email: Prateek <prat.cann.170701@gmail.com>
License: MIT
Project-URL: Homepage, https://github.com/prateek4ai/TimesUserProfilingCumAdRecommendation
Project-URL: Repository, https://github.com/prateek4ai/TimesUserProfilingCumAdRecommendation
Project-URL: Documentation, https://github.com/prateek4ai/TimesUserProfilingCumAdRecommendation#readme
Project-URL: Issues, https://github.com/prateek4ai/TimesUserProfilingCumAdRecommendation/issues
Project-URL: PyPI, https://pypi.org/project/times-ctr-optimizer/
Keywords: ctr-optimization,recommendation-system,machine-learning,ad-tech,sponsored-content,revenue-optimization,click-through-rate,iit-patna,times-network
Classifier: Development Status :: 5 - Production/Stable
Classifier: Intended Audience :: Developers
Classifier: Intended Audience :: Science/Research
Classifier: Intended Audience :: Education
Classifier: Topic :: Scientific/Engineering :: Artificial Intelligence
Classifier: Topic :: Software Development :: Libraries :: Python Modules
Classifier: Topic :: Office/Business :: Financial
Classifier: License :: OSI Approved :: MIT License
Classifier: Programming Language :: Python :: 3
Classifier: Programming Language :: Python :: 3.8
Classifier: Programming Language :: Python :: 3.9
Classifier: Programming Language :: Python :: 3.10
Classifier: Programming Language :: Python :: 3.11
Classifier: Programming Language :: Python :: 3.12
Requires-Python: >=3.8
License-File: LICENSE
Requires-Dist: numpy>=1.21.0
Requires-Dist: pandas>=1.3.0
Requires-Dist: polars>=0.19.0
Requires-Dist: scikit-learn>=1.0.0
Requires-Dist: torch>=1.12.0
Requires-Dist: matplotlib>=3.5.0
Requires-Dist: seaborn>=0.11.0
Requires-Dist: tqdm>=4.60.0
Requires-Dist: rich>=12.0.0
Requires-Dist: pyarrow>=10.0.0
Provides-Extra: dev
Requires-Dist: pytest>=6.0.0; extra == "dev"
Requires-Dist: black>=22.0.0; extra == "dev"
Requires-Dist: flake8>=4.0.0; extra == "dev"
Requires-Dist: mypy>=0.950; extra == "dev"
Provides-Extra: benchmarks
Requires-Dist: plotly>=5.0.0; extra == "benchmarks"
Dynamic: license-file
